python_telegram_payment_bot-11.1.2.dist-info/DESCRIPTION.rst
python_telegram_payment_bot-11.1.2.dist-info/LICENSE.txt
python_telegram_payment_bot-11.1.2.dist-info/METADATA
python_telegram_payment_bot-11.1.2.dist-info/RECORD
python_telegram_payment_bot-11.1.2.dist-info/WHEEL
python_telegram_payment_bot-11.1.2.dist-info/metadata.json
python_telegram_payment_bot-11.1.2.dist-info/top_level.txt
telegram/__init__.py
telegram/__main__.py
telegram/base.py
telegram/bot.py
telegram/callbackquery.py
telegram/chat.py
telegram/chataction.py
telegram/chatmember.py
telegram/choseninlineresult.py
telegram/constants.py
telegram/error.py
telegram/forcereply.py
telegram/keyboardbutton.py
telegram/message.py
telegram/messageentity.py
telegram/parsemode.py
telegram/replykeyboardmarkup.py
telegram/replykeyboardremove.py
telegram/replymarkup.py
telegram/update.py
telegram/user.py
telegram/userprofilephotos.py
telegram/version.py
telegram/webhookinfo.py
telegram/ext/__init__.py
telegram/ext/basepersistence.py
telegram/ext/callbackcontext.py
telegram/ext/callbackqueryhandler.py
telegram/ext/choseninlineresulthandler.py
telegram/ext/commandhandler.py
telegram/ext/conversationhandler.py
telegram/ext/dictpersistence.py
telegram/ext/dispatcher.py
telegram/ext/filters.py
telegram/ext/handler.py
telegram/ext/inlinequeryhandler.py
telegram/ext/jobqueue.py
telegram/ext/messagehandler.py
telegram/ext/messagequeue.py
telegram/ext/picklepersistence.py
telegram/ext/precheckoutqueryhandler.py
telegram/ext/regexhandler.py
telegram/ext/shippingqueryhandler.py
telegram/ext/stringcommandhandler.py
telegram/ext/stringregexhandler.py
telegram/ext/typehandler.py
telegram/ext/updater.py
telegram/files/__init__.py
telegram/files/animation.py
telegram/files/audio.py
telegram/files/chatphoto.py
telegram/files/contact.py
telegram/files/document.py
telegram/files/file.py
telegram/files/inputfile.py
telegram/files/inputmedia.py
telegram/files/location.py
telegram/files/photosize.py
telegram/files/sticker.py
telegram/files/venue.py
telegram/files/video.py
telegram/files/videonote.py
telegram/files/voice.py
telegram/games/__init__.py
telegram/games/callbackgame.py
telegram/games/game.py
telegram/games/gamehighscore.py
telegram/inline/__init__.py
telegram/inline/inlinekeyboardbutton.py
telegram/inline/inlinekeyboardmarkup.py
