Metadata-Version: 2.0
Name: python-telegram-payment-bot
Version: 11.1.2
Summary: We have made you a wrapper you can't refuse
Home-page: https://python-telegram-bot.org/
Author: Leandro Toledo
Author-email: devs@python-telegram-bot.org
License: LGPLv3
Keywords: python telegram bot api wrapper
Platform: UNKNOWN
Classifier: Development Status :: 5 - Production/Stable
Classifier: Intended Audience :: Developers
Classifier: License :: OSI Approved :: GNU Lesser General Public License v3 (LGPLv3)
Classifier: Operating System :: OS Independent
Classifier: Topic :: Software Development :: Libraries :: Python Modules
Classifier: Topic :: Communications :: Chat
Classifier: Topic :: Internet
Classifier: Programming Language :: Python
Classifier: Programming Language :: Python :: 2
Classifier: Programming Language :: Python :: 2.7
Classifier: Programming Language :: Python :: 3
Classifier: Programming Language :: Python :: 3.4
Classifier: Programming Language :: Python :: 3.5
Classifier: Programming Language :: Python :: 3.6
Requires-Dist: certifi
Requires-Dist: cryptography
Requires-Dist: future (>=0.16.0)
Provides-Extra: json
Requires-Dist: ujson; extra == 'json'
Provides-Extra: socks
Requires-Dist: PySocks; extra == 'socks'
